core/__init__.py
core/blockchain.py
core/wallet.py
metanode/__init__.py
metanode/cli.py
metanode/full_sdk.py
metanode/blockchain/__init__.py
metanode/blockchain/cluster.py
metanode/blockchain/core.py
metanode/blockchain/infrastructure.py
metanode/blockchain/storage.py
metanode/blockchain/transaction.py
metanode/blockchain/validator.py
metanode/cli/__init__.py
metanode/cli/commands.py
metanode/cli/main.py
metanode/cloud/__init__.py
metanode/cloud/cli.py
metanode/dapp/__init__.py
metanode/dapp/agent.py
metanode/dapp/api.py
metanode/dapp/connector.py
metanode/dapp/docker_transformer.py
metanode/dapp/fixed_connector.py
metanode/dapp/k8s_transformer.py
metanode/dapp/templates/__init__.py
metanode/dapp/templates/docker-compose.yml
metanode/dapp/templates/docker-lock.yaml
metanode/dapp/templates/k8s-deployment.yaml
metanode/dapp/templates/network-configmap.yaml
metanode/mining/__init__.py
metanode/mining/console.py
metanode/utils/__init__.py
metanode/utils/docker.py
metanode/utils/ipfs_tools.py
metanode/utils/zk_proofs.py
metanode/wallet/__init__.py
metanode/wallet/cli.py
metanode/wallet/core.py
metanode/wallet/escrow.py
metanode_sdk-1.1.0.dist-info/LICENSE
metanode_sdk-1.1.0.dist-info/METADATA
metanode_sdk-1.1.0.dist-info/WHEEL
metanode_sdk-1.1.0.dist-info/entry_points.txt
metanode_sdk-1.1.0.dist-info/top_level.txt
metanode_sdk-1.1.0.dist-info/RECORD
